Metadata-Version: 2.4
Name: mcp-server-motherduck
Version: 0.8.1
Summary: A MCP server for MotherDuck and local DuckDB
Author-email: tdoehmen <till@motherduck.com>
License-File: LICENSE
Requires-Python: >=3.10
Requires-Dist: anyio>=4.8.0
Requires-Dist: click>=8.1.8
Requires-Dist: duckdb==1.4.3
Requires-Dist: mcp>=1.23.0
Requires-Dist: pytz>=2025.2
Requires-Dist: starlette>=0.49.1
Requires-Dist: tabulate>=0.9.0
Requires-Dist: uvicorn>=0.34.0
